dogpile_mongo/__init__.py
dogpile_mongo/backends.py
tests/__init__.py
tests/test_mongo_backend.py
dogpile_mongo-0.0.1.dist-info/METADATA
dogpile_mongo-0.0.1.dist-info/WHEEL
dogpile_mongo-0.0.1.dist-info/entry_points.txt
dogpile_mongo-0.0.1.dist-info/top_level.txt
dogpile_mongo-0.0.1.dist-info/zip-safe
dogpile_mongo-0.0.1.dist-info/RECORD
