Metadata-Version: 2.1
Name: dogpile-mongo
Version: 0.0.1
Summary: backend for dogpile.cache with reading and writing on mongodb
Home-page: https://bitbucket.org/submax82/dogpile_mongo
Author: Massimo Cavalleri
Author-email: submax@tiscali.it
License: MIT
Keywords: caching
Platform: UNKNOWN
Classifier: Development Status :: 4 - Beta
Classifier: Intended Audience :: Developers
Classifier: License :: OSI Approved :: MIT License
Classifier: Programming Language :: Python
Classifier: Programming Language :: Python :: 3
Requires-Dist: dogpile.cache (>=0.6.2)
Requires-Dist: pymongo
